Workbook

Sheet Employees
A1: EmployeeID | B1: EmployeeName | C1: Department | D1: Market | E1: CommissionPlan | F1: Base Salary
A2: E001 | B2: Tammy Salazar MD | C2: Electronics | D2: North America | E2: Tertiary Volume | F2: 3000
A3: E002 | B3: Julia Kelly | C3: Furniture | D3: Europe | E3: Base Salary + Commission | F3: 2250
A4: E003 | B4: Isaiah Peterson | C4: Industrial | D4: North America | E4: Tiered Commission | F4: 3300
A5: E004 | B5: Amanda Williams | C5: Electronics | D5: North America | E5: Base Rate Only | F5: 0
A6: E005 | B6: Johnny Mata | C6: Furniture | D6: South America | E6: Tiered Commission | F6: 3750
A7: E006 | B7: Michael Payne | C7: Industrial | D7: Europe | E7: Tertiary Volume | F7: 3750
A8: E007 | B8: Sandra Combs | C8: Tools | D8: Europe | E8: Gross Margin | F8: 3750
A9: E008 | B9: Kyle Hall | C9: Agriculture | D9: North America | E9: Base Salary + Commission | F9: 3300
A10: E009 | B10: Dr. Justin Stephens | C10: Agriculture | D10: Africa | E10: Base Salary + Commission | F10: 2250
A11: E010 | B11: Stephanie Hunt DVM | C11: Agriculture | D11: North America | E11: Base Rate Only | F11: 0
A12: E011 | B12: Kayla Sellers | C12: Electronics | D12: Africa | E12: Draw Against Commission | F12: 3750
A13: E012 | B13: Edward Hayes | C13: Agriculture | D13: North America | E13: Tertiary Volume | F13: 3300
... A51: E050 | B51: Joseph Berry | C51: Furniture | D51: Africa | E51: Tiered Commission | F51: 3750

Sheet Customers
A1: CustomerID | B1: CustomerName | C1: CustomerType | D1: Region
A2: C001 | B2: Customer_1 | C2: Enterprise | D2: Europe
A3: C002 | B3: Customer_2 | C3: Retailer | D3: Middle East
A4: C003 | B4: Customer_3 | C4: Wholesaler | D4: Middle East
A5: C004 | B5: Customer_4 | C5: Key Account | D5: Asia
A6: C005 | B6: Customer_5 | C6: Key Account | D6: Asia
A7: C006 | B7: Customer_6 | C7: Retailer | D7: Asia
A8: C007 | B8: Customer_7 | C8: Distributor | D8: Europe
A9: C008 | B9: Customer_8 | C9: Wholesaler | D9: North America
A10: C009 | B10: Customer_9 | C10: Key Account | D10: North America
A11: C010 | B11: Customer_10 | C11: Retailer | D11: South America
A12: C011 | B12: Customer_11 | C12: Wholesaler | D12: South America
... A21: C020 | B21: Customer_20 | C21: Retailer | D21: Europe

Sheet Products
A1: ProductID | B1: ProductName | C1: Department | D1: UnitPrice | E1: CostPrice
A2: P001 | B2: Laptop Pro X | C2: Electronics | D2: 1200 | E2: 800
A3: P002 | B3: Office Chair | C3: Furniture | D3: 150 | E3: 90
A4: P003 | B4: Organic Seeds | C4: Agriculture | D4: 20 | E4: 12
A5: P004 | B5: Industrial Drill | C5: Tools | D5: 500 | E5: 300
A6: P005 | B6: Smartwatch Z | C6: Electronics | D6: 300 | E6: 180
A7: P006 | B7: Solar Panel Kit | C7: Industrial | D7: 2000 | E7: 1400

Sheet Sales
A1: SaleID | B1: Date | C1: ProductID | D1: CustomerID | E1: EmployeeID | F1: Quantity | G1: TotalSaleValue | H1: GrossMargin | I1: CommissionPlan
A2: S0001 | B2: 2025-08-08 | C2: P006 | D2: C019 | E2: E037 | F2: 126 | G2: 252000 | H2: 75600 | I2: Tertiary Volume
A3: S0002 | B3: 2025-08-04 | C3: P004 | D3: C014 | E3: E013 | F3: 29 | G3: 14500 | H3: 5800 | I3: Gross Margin
A4: S0003 | B4: 2025-08-14 | C4: P006 | D4: C014 | E4: E023 | F4: 113 | G4: 226000 | H4: 67800 | I4: Tertiary Volume
A5: S0004 | B5: 2025-08-21 | C5: P004 | D5: C002 | E5: E044 | F5: 172 | G5: 86000 | H5: 34400 | I5: Base Rate Only
A6: S0005 | B6: 2025-08-11 | C6: P001 | D6: C002 | E6: E026 | F6: 191 | G6: 229200 | H6: 76400 | I6: Base Salary + Commission
A7: S0006 | B7: 2025-08-18 | C7: P001 | D7: C008 | E7: E013 | F7: 53 | G7: 63600 | H7: 21200 | I7: Gross Margin
A8: S0007 | B8: 2025-08-09 | C8: P004 | D8: C005 | E8: E028 | F8: 51 | G8: 25500 | H8: 10200 | I8: Gross Margin
A9: S0008 | B9: 2025-08-26 | C9: P004 | D9: C008 | E9: E005 | F9: 118 | G9: 59000 | H9: 23600 | I9: Tiered Commission
A10: S0009 | B10: 2025-08-18 | C10: P005 | D10: C004 | E10: E004 | F10: 171 | G10: 51300 | H10: 20520 | I10: Base Rate Only
A11: S0010 | B11: 2025-08-06 | C11: P001 | D11: C003 | E11: E049 | F11: 65 | G11: 78000 | H11: 26000 | I11: Gross Margin
A12: S0011 | B12: 2025-08-28 | C12: P004 | D12: C016 | E12: E031 | F12: 59 | G12: 29500 | H12: 11800 | I12: Gross Margin
A13: S0012 | B13: 2025-08-01 | C13: P004 | D13: C002 | E13: E011 | F13: 102 | G13: 51000 | H13: 20400 | I13: Draw Against Commission
... A501: S0500 | B501: 2025-08-29 | C501: P002 | D501: C008 | E501: E004 | F501: 176 | G501: 26400 | H501: 10560 | I501: Base Rate Only

Sheet Pivot
A3: Row Labels | B3: Commissions | C3: Total_Sales
A4: Agriculture | B4: 387974.17 | C4: 12317560
A5: Electronics | B5: 236628.61 | C5: 6233420
A6: Furniture | B6: 303856.42 | C6: 8716580
A7: Industrial | B7: 214938.16 | C7: 5485550
A8: Tools | B8: 102761.27 | C8: 4466420
A23: Row Labels | B23: Commissions | C23: Total_Sales
A24: Africa | B24: 195574.1 | C24: 6625170
A25: Asia | B25: 59798.44 | C25: 1846100
A26: Europe | B26: 356468.6 | C26: 9732490
A27: Middle East | B27: 262327.2 | C27: 9067330
A28: North America | B28: 225966.76 | C28: 5997680
A29: South America | B29: 146023.52 | C29: 3950760
A31: Total_Sales
A32: 37219530 | B32: 37219530
A34: Sum of Commission
A35: 1246158.6 | B35: 1246158.6
A37: Count of EmployeeID
A38: 50 | B38: 50
A43: Row Labels | B43: Commissions | D43: Commision Plan | E43: Commissions
A44: Base Rate Only | B44: 198141 | D44: Base Rate Only | E44: 198141
A45: Base Salary + Commission | B45: 131415.6 | D45: Base Salary + Commission | E45: 131415.6
A46: Draw Against Commission | B46: 114720.3 | D46: Draw Against Commission | E46: 114720.3
A47: Gross Margin | B47: 103478.32 | D47: Gross Margin | E47: 103478.32
A48: Tertiary Volume | B48: 419405.6 | D48: Tertiary Volume | E48: 419405.6
A49: Tiered Commission | B49: 278997.8 | D49: Tiered Commission | E49: 278997.8

Sheet Analysis

Sheet Employees + Sales
A1: EmployeeID | B1: EmployeeName | C1: Department | D1: Market | E1: CommissionPlan | F1: Base Salary | G1: Total Sales | H1: Gross Margin | I1: Commission
A2: E001 | B2: Tammy Salazar MD | C2: Electronics | D2: North America | E2: Tertiary Volume | F2: 3000 | G2: =SUMIF(Sales!$E$2:$E$501,'Employees + Sales'!A2,Sales!$G$2:$G$501) -> 463620 | H2: =SUMIF(Sales!$E$2:$E$501,Employee_table[[#This Row],[EmployeeID]],Sales!$H$2:$H$501) -> 150168 | I2: =IFERROR(VLOOKUP(Employee_table[[#This Row],[EmployeeID]],'Base Rates Only '!$D$8:$G$14,4,FALSE),IFERROR(VLOOKUP(Employee_table[[#This Row],[EmployeeID]],'Base Salary + commission'!$E$8:$I$16,5,FALSE),IFERROR(VLOOKUP(Employee_table[[#This Row],[EmployeeID]],'Draw Against'!$E$8:$K$13,7,FALSE),IFERROR(VLOOKUP(Employee_table[[#This Row],[EmployeeID]],'Gross Margin'!$E$8:$I$16,5,FALSE),IFERROR(VLOOKUP(Employee_table[[#This Row],[EmployeeID]],'Tiered Commission'!$E$7:$H$13,4,FALSE),IFERROR(VLOOKUP(Employee_table[[#This Row],[EmployeeID]],'Tertiary Volume'!$E$8:$H$19,4,FALSE),"No")))))) -> 33847.467
A3: E002 | B3: Julia Kelly | C3: Furniture | D3: Europe | E3: Base Salary + Commission | F3: 2250 | G3: =SUMIF(Sales!$E$2:$E$501,'Employees + Sales'!A3,Sales!$G$2:$G$501) -> 277010 | H3: =SUMIF(Sales!$E$2:$E$501,Employee_table[[#This Row],[EmployeeID]],Sales!$H$2:$H$501) -> 95124 | I3: =IFERROR(VLOOKUP(Employee_table[[#This Row],[EmployeeID]],'Base Rates Only '!$D$8:$G$14,4,FALSE),IFERROR(VLOOKUP(Employee_table[[#This Row],[EmployeeID]],'Base Salary + commission'!$E$8:$I$16,5,FALSE),IFERROR(VLOOKUP(Employee_table[[#This Row],[EmployeeID]],'Draw Against'!$E$8:$K$13,7,FALSE),IFERROR(VLOOKUP(Employee_table[[#This Row],[EmployeeID]],'Gross Margin'!$E$8:$I$16,5,FALSE),IFERROR(VLOOKUP(Employee_table[[#This Row],[EmployeeID]],'Tiered Commission'!$E$7:$H$13,4,FALSE),IFERROR(VLOOKUP(Employee_table[[#This Row],[EmployeeID]],'Tertiary Volume'!$E$8:$H$19,4,FALSE),"No")))))) -> 7790.2
A4: E003 | B4: Isaiah Peterson | C4: Industrial | D4: North America | E4: Tiered Commission | F4: 3300 | G4: =SUMIF(Sales!$E$2:$E$501,'Employees + Sales'!A4,Sales!$G$2:$G$501) -> 659280 | H4: =SUMIF(Sales!$E$2:$E$501,Employee_table[[#This Row],[EmployeeID]],Sales!$H$2:$H$501) -> 221112 | I4: =IFERROR(VLOOKUP(Employee_table[[#This Row],[EmployeeID]],'Base Rates Only '!$D$8:$G$14,4,FALSE),IFERROR(VLOOKUP(Employee_table[[#This Row],[EmployeeID]],'Base Salary + commission'!$E$8:$I$16,5,FALSE),IFERROR(VLOOKUP(Employee_table[[#This Row],[EmployeeID]],'Draw Against'!$E$8:$K$13,7,FALSE),IFERROR(VLOOKUP(Employee_table[[#This Row],[EmployeeID]],'Gross Margin'!$E$8:$I$16,5,FALSE),IFERROR(VLOOKUP(Employee_table[[#This Row],[EmployeeID]],'Tiered Commission'!$E$7:$H$13,4,FALSE),IFERROR(VLOOKUP(Employee_table[[#This Row],[EmployeeID]],'Tertiary Volume'!$E$8:$H$19,4,FALSE),"No")))))) -> 19778.4
A5: E004 | B5: Amanda Williams | C5: Electronics | D5: North America | E5: Base Rate Only | F5: 0 | G5: =SUMIF(Sales!$E$2:$E$501,'Employees + Sales'!A5,Sales!$G$2:$G$501) -> 204540 | H5: =SUMIF(Sales!$E$2:$E$501,Employee_table[[#This Row],[EmployeeID]],Sales!$H$2:$H$501) -> 78416 | I5: =IFERROR(VLOOKUP(Employee_table[[#This Row],[EmployeeID]],'Base Rates Only '!$D$8:$G$14,4,FALSE),IFERROR(VLOOKUP(Employee_table[[#This Row],[EmployeeID]],'Base Salary + commission'!$E$8:$I$16,5,FALSE),IFERROR(VLOOKUP(Employee_table[[#This Row],[EmployeeID]],'Draw Against'!$E$8:$K$13,7,FALSE),IFERROR(VLOOKUP(Employee_table[[#This Row],[EmployeeID]],'Gross Margin'!$E$8:$I$16,5,FALSE),IFERROR(VLOOKUP(Employee_table[[#This Row],[EmployeeID]],'Tiered Commission'!$E$7:$H$13,4,FALSE),IFERROR(VLOOKUP(Employee_table[[#This Row],[EmployeeID]],'Tertiary Volume'!$E$8:$H$19,4,FALSE),"No")))))) -> 10227
A6: E005 | B6: Johnny Mata | C6: Furniture | D6: South America | E6: Tiered Commission | F6: 3750 | G6: =SUMIF(Sales!$E$2:$E$501,'Employees + Sales'!A6,Sales!$G$2:$G$501) -> 1006320 | H6: =SUMIF(Sales!$E$2:$E$501,Employee_table[[#This Row],[EmployeeID]],Sales!$H$2:$H$501) -> 311648 | I6: =IFERROR(VLOOKUP(Employee_table[[#This Row],[EmployeeID]],'Base Rates Only '!$D$8:$G$14,4,FALSE),IFERROR(VLOOKUP(Employee_table[[#This Row],[EmployeeID]],'Base Salary + commission'!$E$8:$I$16,5,FALSE),IFERROR(VLOOKUP(Employee_table[[#This Row],[EmployeeID]],'Draw Against'!$E$8:$K$13,7,FALSE),IFERROR(VLOOKUP(Employee_table[[#This Row],[EmployeeID]],'Gross Margin'!$E$8:$I$16,5,FALSE),IFERROR(VLOOKUP(Employee_table[[#This Row],[EmployeeID]],'Tiered Commission'!$E$7:$H$13,4,FALSE),IFERROR(VLOOKUP(Employee_table[[#This Row],[EmployeeID]],'Tertiary Volume'!$E$8:$H$19,4,FALSE),"No")))))) -> 50316
A7: E006 | B7: Michael Payne | C7: Industrial | D7: Europe | E7: Tertiary Volume | F7: 3750 | G7: =SUMIF(Sales!$E$2:$E$501,'Employees + Sales'!A7,Sales!$G$2:$G$501) -> 902400 | H7: =SUMIF(Sales!$E$2:$E$501,Employee_table[[#This Row],[EmployeeID]],Sales!$H$2:$H$501) -> 294560 | I7: =IFERROR(VLOOKUP(Employee_table[[#This Row],[EmployeeID]],'Base Rates Only '!$D$8:$G$14,4,FALSE),IFERROR(VLOOKUP(Employee_table[[#This Row],[EmployeeID]],'Base Salary + commission'!$E$8:$I$16,5,FALSE),IFERROR(VLOOKUP(Employee_table[[#This Row],[EmployeeID]],'Draw Against'!$E$8:$K$13,7,FALSE),IFERROR(VLOOKUP(Employee_table[[#This Row],[EmployeeID]],'Gross Margin'!$E$8:$I$16,5,FALSE),IFERROR(VLOOKUP(Employee_table[[#This Row],[EmployeeID]],'Tiered Commission'!$E$7:$H$13,4,FALSE),IFERROR(VLOOKUP(Employee_table[[#This Row],[EmployeeID]],'Tertiary Volume'!$E$8:$H$19,4,FALSE),"No")))))) -> 58089.6
A8: E007 | B8: Sandra Combs | C8: Tools | D8: Europe | E8: Gross Margin | F8: 3750 | G8: =SUMIF(Sales!$E$2:$E$501,'Employees + Sales'!A8,Sales!$G$2:$G$501) -> 976640 | H8: =SUMIF(Sales!$E$2:$E$501,Employee_table[[#This Row],[EmployeeID]],Sales!$H$2:$H$501) -> 315816 | I8: =IFERROR(VLOOKUP(Employee_table[[#This Row],[EmployeeID]],'Base Rates Only '!$D$8:$G$14,4,FALSE),IFERROR(VLOOKUP(Employee_table[[#This Row],[EmployeeID]],'Base Salary + commission'!$E$8:$I$16,5,FALSE),IFERROR(VLOOKUP(Employee_table[[#This Row],[EmployeeID]],'Draw Against'!$E$8:$K$13,7,FALSE),IFERROR(VLOOKUP(Employee_table[[#This Row],[EmployeeID]],'Gross Margin'!$E$8:$I$16,5,FALSE),IFERROR(VLOOKUP(Employee_table[[#This Row],[EmployeeID]],'Tiered Commission'!$E$7:$H$13,4,FALSE),IFERROR(VLOOKUP(Employee_table[[#This Row],[EmployeeID]],'Tertiary Volume'!$E$8:$H$19,4,FALSE),"No")))))) -> 17369.88
A9: E008 | B9: Kyle Hall | C9: Agriculture | D9: North America | E9: Base Salary + Commission | F9: 3300 | G9: =SUMIF(Sales!$E$2:$E$501,'Employees + Sales'!A9,Sales!$G$2:$G$501) -> 132880 | H9: =SUMIF(Sales!$E$2:$E$501,Employee_table[[#This Row],[EmployeeID]],Sales!$H$2:$H$501) -> 50752 | I9: =IFERROR(VLOOKUP(Employee_table[[#This Row],[EmployeeID]],'Base Rates Only '!$D$8:$G$14,4,FALSE),IFERROR(VLOOKUP(Employee_table[[#This Row],[EmployeeID]],'Base Salary + commission'!$E$8:$I$16,5,FALSE),IFERROR(VLOOKUP(Employee_table[[#This Row],[EmployeeID]],'Draw Against'!$E$8:$K$13,7,FALSE),IFERROR(VLOOKUP(Employee_table[[#This Row],[EmployeeID]],'Gross Margin'!$E$8:$I$16,5,FALSE),IFERROR(VLOOKUP(Employee_table[[#This Row],[EmployeeID]],'Tiered Commission'!$E$7:$H$13,4,FALSE),IFERROR(VLOOKUP(Employee_table[[#This Row],[EmployeeID]],'Tertiary Volume'!$E$8:$H$19,4,FALSE),"No")))))) -> 5957.6
A10: E009 | B10: Dr. Justin Stephens | C10: Agriculture | D10: Africa | E10: Base Salary + Commission | F10: 2250 | G10: =SUMIF(Sales!$E$2:$E$501,'Employees + Sales'!A10,Sales!$G$2:$G$501) -> 1056570 | H10: =SUMIF(Sales!$E$2:$E$501,Employee_table[[#This Row],[EmployeeID]],Sales!$H$2:$H$501) -> 355148 | I10: =IFERROR(VLOOKUP(Employee_table[[#This Row],[EmployeeID]],'Base Rates Only '!$D$8:$G$14,4,FALSE),IFERROR(VLOOKUP(Employee_table[[#This Row],[EmployeeID]],'Base Salary + commission'!$E$8:$I$16,5,FALSE),IFERROR(VLOOKUP(Employee_table[[#This Row],[EmployeeID]],'Draw Against'!$E$8:$K$13,7,FALSE),IFERROR(VLOOKUP(Employee_table[[#This Row],[EmployeeID]],'Gross Margin'!$E$8:$I$16,5,FALSE),IFERROR(VLOOKUP(Employee_table[[#This Row],[EmployeeID]],'Tiered Commission'!$E$7:$H$13,4,FALSE),IFERROR(VLOOKUP(Employee_table[[#This Row],[EmployeeID]],'Tertiary Volume'!$E$8:$H$19,4,FALSE),"No")))))) -> 23381.4
A11: E010 | B11: Stephanie Hunt DVM | C11: Agriculture | D11: North America | E11: Base Rate Only | F11: 0 | G11: =SUMIF(Sales!$E$2:$E$501,'Employees + Sales'!A11,Sales!$G$2:$G$501) -> 389040 | H11: =SUMIF(Sales!$E$2:$E$501,Employee_table[[#This Row],[EmployeeID]],Sales!$H$2:$H$501) -> 125816 | I11: =IFERROR(VLOOKUP(Employee_table[[#This Row],[EmployeeID]],'Base Rates Only '!$D$8:$G$14,4,FALSE),IFERROR(VLOOKUP(Employee_table[[#This Row],[EmployeeID]],'Base Salary + commission'!$E$8:$I$16,5,FALSE),IFERROR(VLOOKUP(Employee_table[[#This Row],[EmployeeID]],'Draw Against'!$E$8:$K$13,7,FALSE),IFERROR(VLOOKUP(Employee_table[[#This Row],[EmployeeID]],'Gross Margin'!$E$8:$I$16,5,FALSE),IFERROR(VLOOKUP(Employee_table[[#This Row],[EmployeeID]],'Tiered Commission'!$E$7:$H$13,4,FALSE),IFERROR(VLOOKUP(Employee_table[[#This Row],[EmployeeID]],'Tertiary Volume'!$E$8:$H$19,4,FALSE),"No")))))) -> 19452
A12: E011 | B12: Kayla Sellers | C12: Electronics | D12: Africa | E12: Draw Against Commission | F12: 3750 | G12: =SUMIF(Sales!$E$2:$E$501,'Employees + Sales'!A12,Sales!$G$2:$G$501) -> 486440 | H12: =SUMIF(Sales!$E$2:$E$501,Employee_table[[#This Row],[EmployeeID]],Sales!$H$2:$H$501) -> 171736 | I12: =IFERROR(VLOOKUP(Employee_table[[#This Row],[EmployeeID]],'Base Rates Only '!$D$8:$G$14,4,FALSE),IFERROR(VLOOKUP(Employee_table[[#This Row],[EmployeeID]],'Base Salary + commission'!$E$8:$I$16,5,FALSE),IFERROR(VLOOKUP(Employee_table[[#This Row],[EmployeeID]],'Draw Against'!$E$8:$K$13,7,FALSE),IFERROR(VLOOKUP(Employee_table[[#This Row],[EmployeeID]],'Gross Margin'!$E$8:$I$16,5,FALSE),IFERROR(VLOOKUP(Employee_table[[#This Row],[EmployeeID]],'Tiered Commission'!$E$7:$H$13,4,FALSE),IFERROR(VLOOKUP(Employee_table[[#This Row],[EmployeeID]],'Tertiary Volume'!$E$8:$H$19,4,FALSE),"No")))))) -> 10843.2
A13: E012 | B13: Edward Hayes | C13: Agriculture | D13: North America | E13: Tertiary Volume | F13: 3300 | G13: =SUMIF(Sales!$E$2:$E$501,'Employees + Sales'!A13,Sales!$G$2:$G$501) -> 744900 | H13: =SUMIF(Sales!$E$2:$E$501,Employee_table[[#This Row],[EmployeeID]],Sales!$H$2:$H$501) -> 250000 | I13: =IFERROR(VLOOKUP(Employee_table[[#This Row],[EmployeeID]],'Base Rates Only '!$D$8:$G$14,4,FALSE),IFERROR(VLOOKUP(Employee_table[[#This Row],[EmployeeID]],'Base Salary + commission'!$E$8:$I$16,5,FALSE),IFERROR(VLOOKUP(Employee_table[[#This Row],[EmployeeID]],'Draw Against'!$E$8:$K$13,7,FALSE),IFERROR(VLOOKUP(Employee_table[[#This Row],[EmployeeID]],'Gross Margin'!$E$8:$I$16,5,FALSE),IFERROR(VLOOKUP(Employee_table[[#This Row],[EmployeeID]],'Tiered Commission'!$E$7:$H$13,4,FALSE),IFERROR(VLOOKUP(Employee_table[[#This Row],[EmployeeID]],'Tertiary Volume'!$E$8:$H$19,4,FALSE),"No")))))) -> 33847.467
... A51: E050 | B51: Joseph Berry | C51: Furniture | D51: Africa | E51: Tiered Commission | F51: 3750 | G51: =SUMIF(Sales!$E$2:$E$501,'Employees + Sales'!A51,Sales!$G$2:$G$501) -> 1056700 | H51: =SUMIF(Sales!$E$2:$E$501,Employee_table[[#This Row],[EmployeeID]],Sales!$H$2:$H$501) -> 334880 | I51: =IFERROR(VLOOKUP(Employee_table[[#This Row],[EmployeeID]],'Base Rates Only '!$D$8:$G$14,4,FALSE),IFERROR(VLOOKUP(Employee_table[[#This Row],[EmployeeID]],'Base Salary + commission'!$E$8:$I$16,5,FALSE),IFERROR(VLOOKUP(Employee_table[[#This Row],[EmployeeID]],'Draw Against'!$E$8:$K$13,7,FALSE),IFERROR(VLOOKUP(Employee_table[[#This Row],[EmployeeID]],'Gross Margin'!$E$8:$I$16,5,FALSE),IFERROR(VLOOKUP(Employee_table[[#This Row],[EmployeeID]],'Tiered Commission'!$E$7:$H$13,4,FALSE),IFERROR(VLOOKUP(Employee_table[[#This Row],[EmployeeID]],'Tertiary Volume'!$E$8:$H$19,4,FALSE),"No")))))) -> 52835

Sheet Base Rates Only 
B2: Commision Plan | C2: Base Rate Only
B3: Commision Rate | C3: 0.05
D7: Employee ID | E7: Commission Rates | F7: Gross Sales | G7: Commission Total
D8: {=_xlfn._xlws.FILTER(Employee_table[EmployeeID],Employee_table[CommissionPlan]='Base Rates Only '!$C$2)} -> E004 | E8: =$C$3 -> 0.05 | F8: =_xlfn.XLOOKUP(D8,Employee_table[EmployeeID],Employee_table[Total Sales],0,0) -> 204540 | G8: =F8*E8 -> 10227
D9: E010 | E9: =$C$3 -> 0.05 | F9: =_xlfn.XLOOKUP(D9,Employee_table[EmployeeID],Employee_table[Total Sales],0,0) -> 389040 | G9: =F9*E9 -> 19452
D10: E017 | E10: =$C$3 -> 0.05 | F10: =_xlfn.XLOOKUP(D10,Employee_table[EmployeeID],Employee_table[Total Sales],0,0) -> 1221220 | G10: =F10*E10 -> 61061
D11: E033 | E11: =$C$3 -> 0.05 | F11: =_xlfn.XLOOKUP(D11,Employee_table[EmployeeID],Employee_table[Total Sales],0,0) -> 714200 | G11: =F11*E11 -> 35710
D12: E044 | E12: =$C$3 -> 0.05 | F12: =_xlfn.XLOOKUP(D12,Employee_table[EmployeeID],Employee_table[Total Sales],0,0) -> 238000 | G12: =F12*E12 -> 11900
D13: E045 | E13: =$C$3 -> 0.05 | F13: =_xlfn.XLOOKUP(D13,Employee_table[EmployeeID],Employee_table[Total Sales],0,0) -> 492880 | G13: =F13*E13 -> 24644
D14: E047 | E14: =$C$3 -> 0.05 | F14: =_xlfn.XLOOKUP(D14,Employee_table[EmployeeID],Employee_table[Total Sales],0,0) -> 702940 | G14: =F14*E14 -> 35147

Sheet Base Salary + commission
B2: Commision Plan | C2: Base Salary + Commission
B3: Commision Rate | C3: 0.02
E7: Employee ID | F7: Base Pay (Salary) | G7: Gross Sales | H7: Commission Rates | I7: Total Pay
E8: {=_xlfn._xlws.FILTER(Employee_table[EmployeeID],Employee_table[CommissionPlan]='Base Salary + commission'!$C$2)} -> E002 | F8: =VLOOKUP(E8,Employee_table[],6,FALSE) -> 2250 | G8: =VLOOKUP(E8,Employee_table[],7,FALSE) -> 277010 | H8: =$C$3 -> 0.02 | I8: =F8+H8*G8 -> 7790.2
E9: E008 | F9: =VLOOKUP(E9,Employee_table[],6,FALSE) -> 3300 | G9: =VLOOKUP(E9,Employee_table[],7,FALSE) -> 132880 | H9: =$C$3 -> 0.02 | I9: =F9+H9*G9 -> 5957.6
E10: E009 | F10: =VLOOKUP(E10,Employee_table[],6,FALSE) -> 2250 | G10: =VLOOKUP(E10,Employee_table[],7,FALSE) -> 1056570 | H10: =$C$3 -> 0.02 | I10: =F10+H10*G10 -> 23381.4
E11: E015 | F11: =VLOOKUP(E11,Employee_table[],6,FALSE) -> 3750 | G11: =VLOOKUP(E11,Employee_table[],7,FALSE) -> 749840 | H11: =$C$3 -> 0.02 | I11: =F11+H11*G11 -> 18746.8
E12: E016 | F12: =VLOOKUP(E12,Employee_table[],6,FALSE) -> 3000 | G12: =VLOOKUP(E12,Employee_table[],7,FALSE) -> 704500 | H12: =$C$3 -> 0.02 | I12: =F12+H12*G12 -> 17090
E13: E021 | F13: =VLOOKUP(E13,Employee_table[],6,FALSE) -> 3750 | G13: =VLOOKUP(E13,Employee_table[],7,FALSE) -> 450950 | H13: =$C$3 -> 0.02 | I13: =F13+H13*G13 -> 12769
E14: E026 | F14: =VLOOKUP(E14,Employee_table[],6,FALSE) -> 3750 | G14: =VLOOKUP(E14,Employee_table[],7,FALSE) -> 391800 | H14: =$C$3 -> 0.02 | I14: =F14+H14*G14 -> 11586
E15: E029 | F15: =VLOOKUP(E15,Employee_table[],6,FALSE) -> 3750 | G15: =VLOOKUP(E15,Employee_table[],7,FALSE) -> 1235960 | H15: =$C$3 -> 0.02 | I15: =F15+H15*G15 -> 28469.2
E16: E046 | F16: =VLOOKUP(E16,Employee_table[],6,FALSE) -> 3000 | G16: =VLOOKUP(E16,Employee_table[],7,FALSE) -> 131270 | H16: =$C$3 -> 0.02 | I16: =F16+H16*G16 -> 5625.4

Sheet Draw Against
B2: Commision Plan | C2: Draw Against Commission
B3: Commision Rate | C3: 0.03
E7: Employee ID | F7: Total Sales | G7: Commission Rates | H7: Commission Earned | I7: Draw Amount | J7: Recovery Amount | K7: Commission Payout
E8: {=_xlfn._xlws.FILTER(Employee_table[EmployeeID],Employee_table[CommissionPlan]='Draw Against'!$C$2)} -> E011 | F8: =VLOOKUP(E8,Employee_table[],7,FALSE) -> 486440 | G8: =$C$3 -> 0.03 | H8: =G8*F8 -> 14593.2 | I8: =VLOOKUP(E8,Employee_table[],6,FALSE) -> 3750 | J8: =IF(I8>H8,I8-H8,0) -> 0 | K8: =IF(H8>I8,H8-I8,0) -> 10843.2
E9: E019 | F9: =VLOOKUP(E9,Employee_table[],7,FALSE) -> 1180600 | G9: =$C$3 -> 0.03 | H9: =G9*F9 -> 35418 | I9: =VLOOKUP(E9,Employee_table[],6,FALSE) -> 2250 | J9: =IF(I9>H9,I9-H9,0) -> 0 | K9: =IF(H9>I9,H9-I9,0) -> 33168
E10: E024 | F10: =VLOOKUP(E10,Employee_table[],7,FALSE) -> 856960 | G10: =$C$3 -> 0.03 | H10: =G10*F10 -> 25708.8 | I10: =VLOOKUP(E10,Employee_table[],6,FALSE) -> 3000 | J10: =IF(I10>H10,I10-H10,0) -> 0 | K10: =IF(H10>I10,H10-I10,0) -> 22708.8
E11: E025 | F11: =VLOOKUP(E11,Employee_table[],7,FALSE) -> 90320 | G11: =$C$3 -> 0.03 | H11: =G11*F11 -> 2709.6 | I11: =VLOOKUP(E11,Employee_table[],6,FALSE) -> 3300 | J11: =IF(I11>H11,I11-H11,0) -> 590.4 | K11: =IF(H11>I11,H11-I11,0) -> 0
E12: E036 | F12: =VLOOKUP(E12,Employee_table[],7,FALSE) -> 873150 | G12: =$C$3 -> 0.03 | H12: =G12*F12 -> 26194.5 | I12: =VLOOKUP(E12,Employee_table[],6,FALSE) -> 3750 | J12: =IF(I12>H12,I12-H12,0) -> 0 | K12: =IF(H12>I12,H12-I12,0) -> 22444.5
E13: E043 | F13: =VLOOKUP(E13,Employee_table[],7,FALSE) -> 926860 | G13: =$C$3 -> 0.03 | H13: =G13*F13 -> 27805.8 | I13: =VLOOKUP(E13,Employee_table[],6,FALSE) -> 2250 | J13: =IF(I13>H13,I13-H13,0) -> 0 | K13: =IF(H13>I13,H13-I13,0) -> 25555.8

Sheet Gross Margin
B2: Commision Plan | C2: Gross Margin
B3: Commision Rate | C3: 0.055
E7: Employee ID | F7: Total Sales | G7: Gross Margin | H7: Commission Rates | I7: Total Pay
E8: {=_xlfn._xlws.FILTER(Employee_table[EmployeeID],Employee_table[CommissionPlan]='Gross Margin'!$C$2)} -> E007 | F8: =VLOOKUP(E8,Employee_table[],7,FALSE) -> 976640 | G8: =VLOOKUP(E8,Employee_table[],8,FALSE) -> 315816 | H8: =$C$3 -> 0.055 | I8: =G8*H8 -> 17369.88
E9: E013 | F9: =VLOOKUP(E9,Employee_table[],7,FALSE) -> 469480 | G9: =VLOOKUP(E9,Employee_table[],8,FALSE) -> 172472 | H9: =$C$3 -> 0.055 | I9: =G9*H9 -> 9485.96
E10: E022 | F10: =VLOOKUP(E10,Employee_table[],7,FALSE) -> 327310 | G10: =VLOOKUP(E10,Employee_table[],8,FALSE) -> 125324 | H10: =$C$3 -> 0.055 | I10: =G10*H10 -> 6892.82
E11: E028 | F11: =VLOOKUP(E11,Employee_table[],7,FALSE) -> 498500 | G11: =VLOOKUP(E11,Employee_table[],8,FALSE) -> 170960 | H11: =$C$3 -> 0.055 | I11: =G11*H11 -> 9402.8
E12: E031 | F12: =VLOOKUP(E12,Employee_table[],7,FALSE) -> 380510 | G12: =VLOOKUP(E12,Employee_table[],8,FALSE) -> 135804 | H12: =$C$3 -> 0.055 | I12: =G12*H12 -> 7469.22
E13: E034 | F13: =VLOOKUP(E13,Employee_table[],7,FALSE) -> 714570 | G13: =VLOOKUP(E13,Employee_table[],8,FALSE) -> 244428 | H13: =$C$3 -> 0.055 | I13: =G13*H13 -> 13443.54
E14: E035 | F14: =VLOOKUP(E14,Employee_table[],7,FALSE) -> 514720 | G14: =VLOOKUP(E14,Employee_table[],8,FALSE) -> 181808 | H14: =$C$3 -> 0.055 | I14: =G14*H14 -> 9999.44
E15: E039 | F15: =VLOOKUP(E15,Employee_table[],7,FALSE) -> 945750 | G15: =VLOOKUP(E15,Employee_table[],8,FALSE) -> 303380 | H15: =$C$3 -> 0.055 | I15: =G15*H15 -> 16685.9
E16: E049 | F16: =VLOOKUP(E16,Employee_table[],7,FALSE) -> 711580 | G16: =VLOOKUP(E16,Employee_table[],8,FALSE) -> 231432 | H16: =$C$3 -> 0.055 | I16: =G16*H16 -> 12728.76

Sheet Tiered Commission
B2: Commision Plan | C2: Tiered Commission
E6: Employee ID | F6: Total Sales | G6: Commission Rates | H6: Total Pay
E7: {=_xlfn._xlws.FILTER(Employee_table[EmployeeID],Employee_table[CommissionPlan]='Tiered Commission'!$C$2)} -> E003 | F7: =VLOOKUP(E7,Employee_table[],7,FALSE) -> 659280 | G7: =_xlfn.XLOOKUP(F7,$L$10:$L$16,$M$10:$M$16,,1) -> 0.03 | H7: =F7*G7 -> 19778.4
E8: E005 | F8: =VLOOKUP(E8,Employee_table[],7,FALSE) -> 1006320 | G8: =_xlfn.XLOOKUP(F8,$L$10:$L$16,$M$10:$M$16,,1) -> 0.05 | H8: =F8*G8 -> 50316 | K8: Commission Tiers
E9: E032 | F9: =VLOOKUP(E9,Employee_table[],7,FALSE) -> 865410 | G9: =_xlfn.XLOOKUP(F9,$L$10:$L$16,$M$10:$M$16,,1) -> 0.05 | H9: =F9*G9 -> 43270.5 | K9: Revenue Range | M9: Percentage
E10: E041 | F10: =VLOOKUP(E10,Employee_table[],7,FALSE) -> 997600 | G10: =_xlfn.XLOOKUP(F10,$L$10:$L$16,$M$10:$M$16,,1) -> 0.05 | H10: =F10*G10 -> 49880 | K10: 0 | L10: 333333 | M10: 0.02
E11: E042 | F11: =VLOOKUP(E11,Employee_table[],7,FALSE) -> 1013810 | G11: =_xlfn.XLOOKUP(F11,$L$10:$L$16,$M$10:$M$16,,1) -> 0.05 | H11: =F11*G11 -> 50690.5 | K11: 333334 | L11: 666666 | M11: 0.03
E12: E048 | F12: =VLOOKUP(E12,Employee_table[],7,FALSE) -> 407580 | G12: =_xlfn.XLOOKUP(F12,$L$10:$L$16,$M$10:$M$16,,1) -> 0.03 | H12: =F12*G12 -> 12227.4 | K12: 666667 | L12: 800000 | M12: 0.04
E13: E050 | F13: =VLOOKUP(E13,Employee_table[],7,FALSE) -> 1056700 | G13: =_xlfn.XLOOKUP(F13,$L$10:$L$16,$M$10:$M$16,,1) -> 0.05 | H13: =F13*G13 -> 52835 | K13: 800001 | L13: 1200000 | M13: 0.05
K14: 1200001 | L14: 1600000 | M14: 0.06
K15: 1600001 | L15: 2000000 | M15: 0.07
K16: 2000001 | L16: 10000000 | M16: 0.08

Sheet Tertiary Volume
B2: Commision Plan | C2: Tertiary Volume
E7: Employee ID | F7: Total Sales | G7: Market | H7: Total Pay
E8: {=_xlfn._xlws.FILTER(Employee_table[EmployeeID],Employee_table[CommissionPlan]='Tertiary Volume'!$C$2)} -> E001 | F8: =VLOOKUP(E8,Employee_table[],7,FALSE) -> 463620 | G8: =VLOOKUP(E8,Employee_table[],4,FALSE) -> North America | H8: {=_xlfn.XLOOKUP(G8,_xlfn.ANCHORARRAY($K$10),$N$10:$N$14,0,0)/COUNTIF($G$8:$G$19,G8)} -> 33847.467
E9: E006 | F9: =VLOOKUP(E9,Employee_table[],7,FALSE) -> 902400 | G9: =VLOOKUP(E9,Employee_table[],4,FALSE) -> Europe | H9: {=_xlfn.XLOOKUP(G9,_xlfn.ANCHORARRAY($K$10),$N$10:$N$14,0,0)/COUNTIF($G$8:$G$19,G9)} -> 58089.6 | K9: Market | L9: Total Sales | M9: Percentage | N9: Commision
E10: E012 | F10: =VLOOKUP(E10,Employee_table[],7,FALSE) -> 744900 | G10: =VLOOKUP(E10,Employee_table[],4,FALSE) -> North America | H10: {=_xlfn.XLOOKUP(G10,_xlfn.ANCHORARRAY($K$10),$N$10:$N$14,0,0)/COUNTIF($G$8:$G$19,G10)} -> 33847.467 | K10: {=_xlfn.UNIQUE(_xlfn._xlws.FILTER(Employee_table[Market],Employee_table[CommissionPlan]='Tertiary Volume'!C2))} -> North America | L10: =SUMIFS(Employee_table[Total Sales],Employee_table[Market],'Tertiary Volume'!K10,Employee_table[CommissionPlan],'Tertiary Volume'!$C$2) -> 2538560 | M10: 0.04 | N10: =L10*M10 -> 101542.4
E11: E014 | F11: =VLOOKUP(E11,Employee_table[],7,FALSE) -> 768380 | G11: =VLOOKUP(E11,Employee_table[],4,FALSE) -> Africa | H11: {=_xlfn.XLOOKUP(G11,_xlfn.ANCHORARRAY($K$10),$N$10:$N$14,0,0)/COUNTIF($G$8:$G$19,G11)} -> 17678.4 | K11: Europe | L11: =SUMIFS(Employee_table[Total Sales],Employee_table[Market],'Tertiary Volume'!K11,Employee_table[CommissionPlan],'Tertiary Volume'!$C$2) -> 2904480 | M11: 0.04 | N11: =L11*M11 -> 116179.2
E12: E018 | F12: =VLOOKUP(E12,Employee_table[],7,FALSE) -> 838500 | G12: =VLOOKUP(E12,Employee_table[],4,FALSE) -> Asia | H12: {=_xlfn.XLOOKUP(G12,_xlfn.ANCHORARRAY($K$10),$N$10:$N$14,0,0)/COUNTIF($G$8:$G$19,G12)} -> 25155 | K12: Africa | L12: =SUMIFS(Employee_table[Total Sales],Employee_table[Market],'Tertiary Volume'!K12,Employee_table[CommissionPlan],'Tertiary Volume'!$C$2) -> 1767840 | M12: 0.03 | N12: =L12*M12 -> 53035.2
E13: E020 | F13: =VLOOKUP(E13,Employee_table[],7,FALSE) -> 1407650 | G13: =VLOOKUP(E13,Employee_table[],4,FALSE) -> Middle East | H13: {=_xlfn.XLOOKUP(G13,_xlfn.ANCHORARRAY($K$10),$N$10:$N$14,0,0)/COUNTIF($G$8:$G$19,G13)} -> 41164.6 | K13: Asia | L13: =SUMIFS(Employee_table[Total Sales],Employee_table[Market],'Tertiary Volume'!K13,Employee_table[CommissionPlan],'Tertiary Volume'!$C$2) -> 838500 | M13: 0.03 | N13: =L13*M13 -> 25155
E14: E023 | F14: =VLOOKUP(E14,Employee_table[],7,FALSE) -> 1730380 | G14: =VLOOKUP(E14,Employee_table[],4,FALSE) -> Middle East | H14: {=_xlfn.XLOOKUP(G14,_xlfn.ANCHORARRAY($K$10),$N$10:$N$14,0,0)/COUNTIF($G$8:$G$19,G14)} -> 41164.6 | K14: Middle East | L14: =SUMIFS(Employee_table[Total Sales],Employee_table[Market],'Tertiary Volume'!K14,Employee_table[CommissionPlan],'Tertiary Volume'!$C$2) -> 4116460 | M14: 0.03 | N14: =L14*M14 -> 123493.8
E15: E027 | F15: =VLOOKUP(E15,Employee_table[],7,FALSE) -> 2002080 | G15: =VLOOKUP(E15,Employee_table[],4,FALSE) -> Europe | H15: {=_xlfn.XLOOKUP(G15,_xlfn.ANCHORARRAY($K$10),$N$10:$N$14,0,0)/COUNTIF($G$8:$G$19,G15)} -> 58089.6
E16: E030 | F16: =VLOOKUP(E16,Employee_table[],7,FALSE) -> 730820 | G16: =VLOOKUP(E16,Employee_table[],4,FALSE) -> Africa | H16: {=_xlfn.XLOOKUP(G16,_xlfn.ANCHORARRAY($K$10),$N$10:$N$14,0,0)/COUNTIF($G$8:$G$19,G16)} -> 17678.4
E17: E037 | F17: =VLOOKUP(E17,Employee_table[],7,FALSE) -> 978430 | G17: =VLOOKUP(E17,Employee_table[],4,FALSE) -> Middle East | H17: {=_xlfn.XLOOKUP(G17,_xlfn.ANCHORARRAY($K$10),$N$10:$N$14,0,0)/COUNTIF($G$8:$G$19,G17)} -> 41164.6
E18: E038 | F18: =VLOOKUP(E18,Employee_table[],7,FALSE) -> 268640 | G18: =VLOOKUP(E18,Employee_table[],4,FALSE) -> Africa | H18: {=_xlfn.XLOOKUP(G18,_xlfn.ANCHORARRAY($K$10),$N$10:$N$14,0,0)/COUNTIF($G$8:$G$19,G18)} -> 17678.4
E19: E040 | F19: =VLOOKUP(E19,Employee_table[],7,FALSE) -> 1330040 | G19: =VLOOKUP(E19,Employee_table[],4,FALSE) -> North America | H19: {=_xlfn.XLOOKUP(G19,_xlfn.ANCHORARRAY($K$10),$N$10:$N$14,0,0)/COUNTIF($G$8:$G$19,G19)} -> 33847.467
